challenge_4/lif_neuron.v
module lif_neuron #(
    parameter WIDTH = 16,               // Membrane potential width
    parameter THRESHOLD = 100,          // Spike threshold
    parameter DECAY = 1,                // Leak per time step
    parameter REF_PERIOD = 10           // Refractory period length
)(
    input wire clk,
    input wire rst,
    input wire signed [7:0] input_current,
    output reg spike
);

    reg signed [WIDTH-1:0] V_mem = 0;
    reg [$clog2(REF_PERIOD+1)-1:0] ref_count = 0;

    wire in_refractory = (ref_count != 0);

    always @(posedge clk or posedge rst) begin
        if (rst) begin
            V_mem <= 0;
            spike <= 0;
            ref_count <= 0;
        end else begin
            if (in_refractory) begin
                // Count down refractory period
                ref_count <= ref_count - 1;
                spike <= 0;
            end else begin
                // Integrate input current and apply decay
                V_mem <= V_mem + input_current - DECAY;

                if (V_mem >= THRESHOLD) begin
                    spike <= 1;
                    V_mem <= 0;
                    ref_count <= REF_PERIOD;
                end else begin
                    spike <= 0;
                end
            end
        end
    end
endmodule

challenge_4/tb_lif_neuron_tb.v
`timescale 1ns/1ps

module tb_lif_neuron;

    // Parameters
    parameter WIDTH = 16;
    parameter THRESHOLD = 20;
    parameter DECAY = 1;
    parameter REF_PERIOD = 5;

    // Signals
    reg clk;
    reg rst;
    reg signed [7:0] input_current;
    wire spike;

    // Instantiate neuron
    lif_neuron #(
        .WIDTH(WIDTH),
        .THRESHOLD(THRESHOLD),
        .DECAY(DECAY),
        .REF_PERIOD(REF_PERIOD)
    ) neuron (
        .clk(clk),
        .rst(rst),
        .input_current(input_current),
        .spike(spike)
    );

    // Clock generation
    always #5 clk = ~clk;  // 100 MHz clock

    initial begin
        $display("Starting LIF neuron test...");
        $dumpfile("lif_neuron.vcd");
        $dumpvars(0, tb_lif_neuron);

        // Initialize
        clk = 0;
        rst = 1;
        input_current = 0;
        #10;

        // Release reset
        rst = 0;
        input_current = 5;

        // Run enough time to reach threshold and spike
        repeat (10) begin
            #10;
        end

        // After spike, input still applied, should ignore input during ref
        repeat (10) begin
            #10;
        end

        // Apply negative current (inhibition)
        input_current = -5;
        repeat (5) begin
            #10;
        end

        // Apply a large positive current for fast spike
        input_current = 25;
        repeat (5) begin
            #10;
        end

        $display("Test complete.");
        $finish;
    end
endmodule

challenge_4/lif_neuron.vcd
$date
	Wed Apr  2 15:14:23 2025
$end
$version
	Icarus Verilog
$end
$timescale
	1ps
$end
$scope module tb_lif_neuron $end
$var wire 1 ! spike $end
$var parameter 32 " DECAY $end
$var parameter 32 # REF_PERIOD $end
$var parameter 32 $ THRESHOLD $end
$var parameter 32 % WIDTH $end
$var reg 1 & clk $end
$var reg 8 ' input_current [7:0] $end
$var reg 1 ( rst $end
$scope module neuron $end
$var wire 1 & clk $end
$var wire 8 ) input_current [7:0] $end
$var wire 1 ( rst $end
$var wire 1 * in_refractory $end
$var parameter 32 + DECAY $end
$var parameter 32 , REF_PERIOD $end
$var parameter 32 - THRESHOLD $end
$var parameter 32 . WIDTH $end
$var reg 16 / V_mem [15:0] $end
$var reg 3 0 ref_count [2:0] $end
$var reg 1 ! spike $end
$upscope $end
$upscope $end
$enddefinitions $end
$comment Show the parameter values. $end
$dumpall
b10000 .
b10100 -
b101 ,
b1 +
b10000 %
b10100 $
b101 #
b1 "
$end
#0
$dumpvars
b0 0
b0 /
0*
b0 )
1(
b0 '
0&
0!
$end
#5000
1&
#10000
0&
b101 '
b101 )
0(
#15000
b100 /
1&
#20000
0&
#25000
b1000 /
1&
#30000
0&
#35000
b1100 /
1&
#40000
0&
#45000
b10000 /
1&
#50000
0&
#55000
b10100 /
1&
#60000
0&
#65000
1*
b101 0
1!
b0 /
1&
#70000
0&
#75000
0!
b100 0
1&
#80000
0&
#85000
b11 0
1&
#90000
0&
#95000
b10 0
1&
#100000
0&
#105000
b1 0
1&
#110000
0&
#115000
0*
b0 0
1&
#120000
0&
#125000
b100 /
1&
#130000
0&
#135000
b1000 /
1&
#140000
0&
#145000
b1100 /
1&
#150000
0&
#155000
b10000 /
1&
#160000
0&
#165000
b10100 /
1&
#170000
0&
#175000
1*
b101 0
1!
b0 /
1&
#180000
0&
#185000
0!
b100 0
1&
#190000
0&
#195000
b11 0
1&
#200000
0&
#205000
b10 0
1&
#210000
0&
b11111011 '
b11111011 )
#215000
b1 0
1&
#220000
0&
#225000
0*
b0 0
1&
#230000
0&
#235000
b1111111111111010 /
1&
#240000
0&
#245000
b1111111111110100 /
1&
#250000
0&
#255000
b1111111111101110 /
1&
#260000
0&
b11001 '
b11001 )
#265000
b110 /
1&
#270000
0&
#275000
b11110 /
1&
#280000
0&
#285000
1*
b101 0
1!
b0 /
1&
#290000
0&
#295000
0!
b100 0
1&
#300000
0&
#305000
b11 0
1&
